scrapy_helper/__init__.py
scrapy_helper/__pycache__/__init__.cpython-310.pyc
scrapy_helper/__pycache__/__init__.cpython-311.pyc
scrapy_helper/core/__init__.py
scrapy_helper/core/dict_path.py
scrapy_helper/core/fast_item.py
scrapy_helper/core/urls.py
scrapy_helper/core/utils.py
scrapy_helper/core/__pycache__/__init__.cpython-310.pyc
scrapy_helper/core/__pycache__/dict_path.cpython-310.pyc
scrapy_helper/core/__pycache__/fast_item.cpython-310.pyc
scrapy_helper/core/__pycache__/urls.cpython-310.pyc
scrapy_helper/core/__pycache__/utils.cpython-310.pyc
scrapy_helper/linkextractors/__init__.py
scrapy_helper/linkextractors/article.py
scrapy_helper/linkextractors/__pycache__/__init__.cpython-310.pyc
scrapy_helper/linkextractors/__pycache__/article.cpython-310.pyc
scrapy_helper/middlewares/__init__.py
scrapy_helper/middlewares/__pycache__/__init__.cpython-310.pyc
scrapy_helper/middlewares/downloader/__init__.py
scrapy_helper/middlewares/downloader/cookies.py
scrapy_helper/middlewares/downloader/persist_filter.py
scrapy_helper/middlewares/downloader/proxy.py
scrapy_helper/middlewares/downloader/pyppeteer_middleware.py
scrapy_helper/middlewares/downloader/user_agent.py
scrapy_helper/middlewares/downloader/__pycache__/__init__.cpython-310.pyc
scrapy_helper/middlewares/downloader/__pycache__/cookies.cpython-310.pyc
scrapy_helper/middlewares/downloader/__pycache__/persist_filter.cpython-310.pyc
scrapy_helper/middlewares/downloader/__pycache__/proxy.cpython-310.pyc
scrapy_helper/middlewares/downloader/__pycache__/pyppeteer_middleware.cpython-310.pyc
scrapy_helper/middlewares/downloader/__pycache__/user_agent.cpython-310.pyc
scrapy_helper/middlewares/spider/__init__.py
scrapy_helper/newspaper/__init__.py
scrapy_helper/newspaper/article.py
scrapy_helper/newspaper/cleaners.py
scrapy_helper/newspaper/configuration.py
scrapy_helper/newspaper/extractors.py
scrapy_helper/newspaper/outputformatters.py
scrapy_helper/newspaper/parsers.py
scrapy_helper/newspaper/settings.py
scrapy_helper-1.5.3.dist-info/LICENSE
scrapy_helper-1.5.3.dist-info/METADATA
scrapy_helper-1.5.3.dist-info/WHEEL
scrapy_helper-1.5.3.dist-info/top_level.txt
scrapy_helper-1.5.3.dist-info/RECORD
