Metadata-Version: 2.1
Name: scrapy-helper
Version: 1.5.3
Summary: scrapy helper
Author: Zhou Ping
Author-email: 231409@qq.com
License: Apache 2.0
Keywords: scrapy,spider,helper
Classifier: Framework :: Scrapy
Classifier: Development Status :: 5 - Production/Stable
Classifier: Environment :: Console
Classifier: Intended Audience :: Developers
Classifier: License :: OSI Approved :: BSD License
Classifier: Operating System :: OS Independent
Classifier: Programming Language :: Python
Classifier: Programming Language :: Python :: 3
Classifier: Programming Language :: Python :: 3.7
Classifier: Programming Language :: Python :: 3.8
Classifier: Programming Language :: Python :: 3.9
Classifier: Programming Language :: Python :: 3.10
Classifier: Programming Language :: Python :: 3.11
Classifier: Programming Language :: Python :: Implementation :: CPython
Classifier: Programming Language :: Python :: Implementation :: PyPy
Classifier: Topic :: Internet :: WWW/HTTP
Classifier: Topic :: Software Development :: Libraries :: Application Frameworks
Classifier: Topic :: Software Development :: Libraries :: Python Modules
Requires-Python: >=3.7
License-File: LICENSE
Requires-Dist: PyMySQL (~=1.0.2)
Requires-Dist: Twisted (~=22.8.0)
Requires-Dist: pymongo (~=4.2.0)
Requires-Dist: furl (~=2.1.3)
Requires-Dist: Scrapy (~=2.6.2)
Requires-Dist: websockets (~=10.3)
Requires-Dist: pyppeteer (~=1.0.2)
Requires-Dist: scrapy-splash (~=0.8.0)
Requires-Dist: tldextract (~=3.4.0)
Requires-Dist: lxml (~=4.9.1)
Requires-Dist: bs4 (~=0.0.1)
Requires-Dist: beautifulsoup4 (~=4.11.1)
Requires-Dist: python-dateutil (~=2.8.2)
Requires-Dist: jieba (~=0.42.1)
Requires-Dist: nltk (~=3.7)
Requires-Dist: tinysegmenter (~=0.4)
Requires-Dist: pythainlp (~=3.1.0)
Requires-Dist: requests (~=2.28.1)
Requires-Dist: redis (~=4.3.4)
Requires-Dist: platinum2 (~=1.5.2)
Requires-Dist: itemloaders (~=1.0.6)
